package myobfuscated;

public final class blk
  implements blb
{
  /* Error */
  public final bld a(bkp parambkp, java.util.Map<bkr, ?> paramMap)
    throws bkz, bku
  {
    // Byte code:
    //   0: aconst_null
    //   1: astore 5
    //   3: new 19	myobfuscated/bln
    //   6: dup
    //   7: aload_1
    //   8: invokevirtual 25	myobfuscated/bkp:b	()Lmyobfuscated/blw;
    //   11: invokespecial 28	myobfuscated/bln:<init>	(Lmyobfuscated/blw;)V
    //   14: astore 7
    //   16: aload 7
    //   18: iconst_0
    //   19: invokevirtual 31	myobfuscated/bln:a	(Z)Lmyobfuscated/blj;
    //   22: astore_3
    //   23: aload_3
    //   24: getfield 37	myobfuscated/bmb:e	[Lmyobfuscated/blf;
    //   27: astore_1
    //   28: new 39	myobfuscated/blm
    //   31: dup
    //   32: invokespecial 40	myobfuscated/blm:<init>	()V
    //   35: aload_3
    //   36: invokevirtual 43	myobfuscated/blm:a	(Lmyobfuscated/blj;)Lmyobfuscated/blz;
    //   39: astore 6
    //   41: aconst_null
    //   42: astore 4
    //   44: aload_1
    //   45: astore_3
    //   46: aload 6
    //   48: astore_1
    //   49: aload_1
    //   50: ifnonnull +172 -> 222
    //   53: aload 7
    //   55: iconst_1
    //   56: invokevirtual 31	myobfuscated/bln:a	(Z)Lmyobfuscated/blj;
    //   59: astore_1
    //   60: aload_1
    //   61: getfield 37	myobfuscated/bmb:e	[Lmyobfuscated/blf;
    //   64: astore_3
    //   65: new 39	myobfuscated/blm
    //   68: dup
    //   69: invokespecial 40	myobfuscated/blm:<init>	()V
    //   72: aload_1
    //   73: invokevirtual 43	myobfuscated/blm:a	(Lmyobfuscated/blj;)Lmyobfuscated/blz;
    //   76: astore_1
    //   77: aload_2
    //   78: ifnull +13 -> 91
    //   81: aload_2
    //   82: getstatic 49	myobfuscated/bkr:j	Lmyobfuscated/bkr;
    //   85: invokeinterface 55 2 0
    //   90: pop
    //   91: new 57	myobfuscated/bld
    //   94: dup
    //   95: aload_1
    //   96: getfield 63	myobfuscated/blz:c	Ljava/lang/String;
    //   99: aload_1
    //   100: getfield 66	myobfuscated/blz:a	[B
    //   103: aload_1
    //   104: getfield 69	myobfuscated/blz:b	I
    //   107: aload_3
    //   108: getstatic 74	myobfuscated/bkn:a	Lmyobfuscated/bkn;
    //   111: invokestatic 80	java/lang/System:currentTimeMillis	()J
    //   114: invokespecial 83	myobfuscated/bld:<init>	(Ljava/lang/String;[BI[Lmyobfuscated/blf;Lmyobfuscated/bkn;J)V
    //   117: astore_2
    //   118: aload_1
    //   119: getfield 87	myobfuscated/blz:d	Ljava/util/List;
    //   122: astore_3
    //   123: aload_3
    //   124: ifnull +11 -> 135
    //   127: aload_2
    //   128: getstatic 92	myobfuscated/ble:c	Lmyobfuscated/ble;
    //   131: aload_3
    //   132: invokevirtual 95	myobfuscated/bld:a	(Lmyobfuscated/ble;Ljava/lang/Object;)V
    //   135: aload_1
    //   136: getfield 97	myobfuscated/blz:e	Ljava/lang/String;
    //   139: astore_1
    //   140: aload_1
    //   141: ifnull +11 -> 152
    //   144: aload_2
    //   145: getstatic 99	myobfuscated/ble:d	Lmyobfuscated/ble;
    //   148: aload_1
    //   149: invokevirtual 95	myobfuscated/bld:a	(Lmyobfuscated/ble;Ljava/lang/Object;)V
    //   152: aload_2
    //   153: areturn
    //   154: astore_3
    //   155: aconst_null
    //   156: astore_1
    //   157: aload_1
    //   158: astore 6
    //   160: aconst_null
    //   161: astore_1
    //   162: aload_3
    //   163: astore 4
    //   165: aload 6
    //   167: astore_3
    //   168: goto -119 -> 49
    //   171: astore_3
    //   172: aconst_null
    //   173: astore_1
    //   174: aload_1
    //   175: astore 6
    //   177: aconst_null
    //   178: astore 4
    //   180: aconst_null
    //   181: astore_1
    //   182: aload_3
    //   183: astore 5
    //   185: aload 6
    //   187: astore_3
    //   188: goto -139 -> 49
    //   191: astore_1
    //   192: aload 4
    //   194: ifnull +6 -> 200
    //   197: aload 4
    //   199: athrow
    //   200: aload 5
    //   202: ifnull +6 -> 208
    //   205: aload 5
    //   207: athrow
    //   208: aload_1
    //   209: athrow
    //   210: astore_1
    //   211: goto -19 -> 192
    //   214: astore_3
    //   215: goto -41 -> 174
    //   218: astore_3
    //   219: goto -62 -> 157
    //   222: goto -145 -> 77
    // Local variable table:
    //   start	length	slot	name	signature
    //   0	225	0	this	blk
    //   0	225	1	parambkp	bkp
    //   0	225	2	paramMap	java.util.Map<bkr, ?>
    //   22	110	3	localObject1	Object
    //   154	9	3	localbkz1	bkz
    //   167	1	3	localObject2	Object
    //   171	12	3	localbku1	bku
    //   187	1	3	localObject3	Object
    //   214	1	3	localbku2	bku
    //   218	1	3	localbkz2	bkz
    //   42	156	4	localbkz3	bkz
    //   1	205	5	localObject4	Object
    //   39	147	6	localObject5	Object
    //   14	40	7	localbln	bln
    // Exception table:
    //   from	to	target	type
    //   16	28	154	myobfuscated/bkz
    //   16	28	171	myobfuscated/bku
    //   53	77	191	myobfuscated/bku
    //   53	77	210	myobfuscated/bkz
    //   28	41	214	myobfuscated/bku
    //   28	41	218	myobfuscated/bkz
  }
  
  public final void a() {}
}


/* Location:              C:\dex2jar-2.0\classes-dex2jar.jar!\myobfuscated\blk.class
 * Java compiler version: 6 (50.0)
 * JD-Core Version:       0.7.1
 */