package myobfuscated;

import android.app.ProgressDialog;
import android.os.Handler;
import java.io.Closeable;

public class cnz
{
  private static final String a = cnz.class.getSimpleName();
  
  /* Error */
  public static int a(android.content.Context paramContext, android.net.Uri paramUri)
  {
    // Byte code:
    //   0: aconst_null
    //   1: astore 6
    //   3: aconst_null
    //   4: astore 5
    //   6: aload_1
    //   7: ifnonnull +9 -> 16
    //   10: iconst_0
    //   11: istore 4
    //   13: iload 4
    //   15: ireturn
    //   16: aload_0
    //   17: invokevirtual 35	android/content/Context:getContentResolver	()Landroid/content/ContentResolver;
    //   20: aload_1
    //   21: iconst_1
    //   22: anewarray 37	java/lang/String
    //   25: dup
    //   26: iconst_0
    //   27: ldc 39
    //   29: aastore
    //   30: aconst_null
    //   31: aconst_null
    //   32: aconst_null
    //   33: invokevirtual 45	android/content/ContentResolver:query	(Landroid/net/Uri;[Ljava/lang/String;Ljava/lang/String;[Ljava/lang/String;Ljava/lang/String;)Landroid/database/Cursor;
    //   36: astore 7
    //   38: aload 7
    //   40: ifnull +290 -> 330
    //   43: aload 7
    //   45: invokeinterface 51 1 0
    //   50: ifle +298 -> 348
    //   53: aload 7
    //   55: invokeinterface 55 1 0
    //   60: ifeq +288 -> 348
    //   63: aload 7
    //   65: iconst_0
    //   66: invokeinterface 59 2 0
    //   71: istore_3
    //   72: iconst_1
    //   73: istore_2
    //   74: aload 7
    //   76: ifnull +261 -> 337
    //   79: aload 7
    //   81: invokeinterface 62 1 0
    //   86: ifne +251 -> 337
    //   89: aload 7
    //   91: invokeinterface 65 1 0
    //   96: iload_3
    //   97: istore 4
    //   99: iload_2
    //   100: istore_3
    //   101: iload 4
    //   103: istore_2
    //   104: iload_2
    //   105: istore 4
    //   107: iload_3
    //   108: ifne -95 -> 13
    //   111: aload_0
    //   112: invokevirtual 35	android/content/Context:getContentResolver	()Landroid/content/ContentResolver;
    //   115: aload_1
    //   116: invokevirtual 69	android/content/ContentResolver:openInputStream	(Landroid/net/Uri;)Ljava/io/InputStream;
    //   119: astore_0
    //   120: aload_0
    //   121: astore 5
    //   123: aload_0
    //   124: astore 6
    //   126: new 71	myobfuscated/be
    //   129: dup
    //   130: aload_0
    //   131: invokespecial 74	myobfuscated/be:<init>	(Ljava/io/InputStream;)V
    //   134: ldc 76
    //   136: invokevirtual 80	myobfuscated/be:b	(Ljava/lang/String;)I
    //   139: istore_2
    //   140: iload_2
    //   141: tableswitch	default:+47->188, 1:+113->254, 2:+47->188, 3:+137->278, 4:+47->188, 5:+47->188, 6:+131->272, 7:+47->188, 8:+144->285
    //   188: aload_0
    //   189: ifnull +7 -> 196
    //   192: aload_0
    //   193: invokevirtual 83	java/io/InputStream:close	()V
    //   196: iconst_0
    //   197: ireturn
    //   198: astore 8
    //   200: aload 7
    //   202: ifnull +128 -> 330
    //   205: aload 7
    //   207: invokeinterface 62 1 0
    //   212: ifne +118 -> 330
    //   215: aload 7
    //   217: invokeinterface 65 1 0
    //   222: iconst_0
    //   223: istore_3
    //   224: iconst_0
    //   225: istore_2
    //   226: goto -122 -> 104
    //   229: astore_0
    //   230: aload 7
    //   232: ifnull +20 -> 252
    //   235: aload 7
    //   237: invokeinterface 62 1 0
    //   242: ifne +10 -> 252
    //   245: aload 7
    //   247: invokeinterface 65 1 0
    //   252: aload_0
    //   253: athrow
    //   254: iconst_0
    //   255: istore_2
    //   256: iload_2
    //   257: istore 4
    //   259: aload_0
    //   260: ifnull -247 -> 13
    //   263: aload_0
    //   264: invokevirtual 83	java/io/InputStream:close	()V
    //   267: iload_2
    //   268: ireturn
    //   269: astore_0
    //   270: iload_2
    //   271: ireturn
    //   272: bipush 90
    //   274: istore_2
    //   275: goto -19 -> 256
    //   278: sipush 180
    //   281: istore_2
    //   282: goto -26 -> 256
    //   285: sipush 270
    //   288: istore_2
    //   289: goto -33 -> 256
    //   292: astore_0
    //   293: aload 5
    //   295: ifnull +8 -> 303
    //   298: aload 5
    //   300: invokevirtual 83	java/io/InputStream:close	()V
    //   303: iconst_0
    //   304: ireturn
    //   305: astore_0
    //   306: aload 6
    //   308: ifnull +8 -> 316
    //   311: aload 6
    //   313: invokevirtual 83	java/io/InputStream:close	()V
    //   316: aload_0
    //   317: athrow
    //   318: astore_0
    //   319: goto -123 -> 196
    //   322: astore_0
    //   323: goto -20 -> 303
    //   326: astore_1
    //   327: goto -11 -> 316
    //   330: iconst_0
    //   331: istore_3
    //   332: iconst_0
    //   333: istore_2
    //   334: goto -230 -> 104
    //   337: iload_2
    //   338: istore 4
    //   340: iload_3
    //   341: istore_2
    //   342: iload 4
    //   344: istore_3
    //   345: goto -241 -> 104
    //   348: iconst_0
    //   349: istore_2
    //   350: iconst_0
    //   351: istore_3
    //   352: goto -278 -> 74
    // Local variable table:
    //   start	length	slot	name	signature
    //   0	355	0	paramContext	android.content.Context
    //   0	355	1	paramUri	android.net.Uri
    //   73	277	2	i	int
    //   71	281	3	j	int
    //   11	332	4	k	int
    //   4	295	5	localContext1	android.content.Context
    //   1	311	6	localContext2	android.content.Context
    //   36	210	7	localCursor	android.database.Cursor
    //   198	1	8	localException	Exception
    // Exception table:
    //   from	to	target	type
    //   43	72	198	java/lang/Exception
    //   43	72	229	finally
    //   263	267	269	java/io/IOException
    //   111	120	292	java/io/IOException
    //   126	140	292	java/io/IOException
    //   111	120	305	finally
    //   126	140	305	finally
    //   192	196	318	java/io/IOException
    //   298	303	322	java/io/IOException
    //   311	316	326	java/io/IOException
  }
  
  /* Error */
  public static java.io.File a(android.content.Context paramContext, android.content.ContentResolver paramContentResolver, android.net.Uri paramUri)
  {
    // Byte code:
    //   0: aconst_null
    //   1: astore 4
    //   3: aload_2
    //   4: ifnonnull +7 -> 11
    //   7: aconst_null
    //   8: astore_0
    //   9: aload_0
    //   10: areturn
    //   11: ldc 90
    //   13: aload_2
    //   14: invokevirtual 95	android/net/Uri:getScheme	()Ljava/lang/String;
    //   17: invokevirtual 99	java/lang/String:equals	(Ljava/lang/Object;)Z
    //   20: ifeq +15 -> 35
    //   23: new 101	java/io/File
    //   26: dup
    //   27: aload_2
    //   28: invokevirtual 104	android/net/Uri:getPath	()Ljava/lang/String;
    //   31: invokespecial 107	java/io/File:<init>	(Ljava/lang/String;)V
    //   34: areturn
    //   35: ldc 109
    //   37: aload_2
    //   38: invokevirtual 95	android/net/Uri:getScheme	()Ljava/lang/String;
    //   41: invokevirtual 99	java/lang/String:equals	(Ljava/lang/Object;)Z
    //   44: ifeq +145 -> 189
    //   47: aload_1
    //   48: aload_2
    //   49: iconst_2
    //   50: anewarray 37	java/lang/String
    //   53: dup
    //   54: iconst_0
    //   55: ldc 111
    //   57: aastore
    //   58: dup
    //   59: iconst_1
    //   60: ldc 113
    //   62: aastore
    //   63: aconst_null
    //   64: aconst_null
    //   65: aconst_null
    //   66: invokevirtual 45	android/content/ContentResolver:query	(Landroid/net/Uri;[Ljava/lang/String;Ljava/lang/String;[Ljava/lang/String;Ljava/lang/String;)Landroid/database/Cursor;
    //   69: astore 5
    //   71: aload 5
    //   73: astore 4
    //   75: aload 4
    //   77: ifnull +100 -> 177
    //   80: aload 4
    //   82: invokeinterface 55 1 0
    //   87: ifeq +90 -> 177
    //   90: aload_2
    //   91: invokevirtual 116	android/net/Uri:toString	()Ljava/lang/String;
    //   94: ldc 118
    //   96: invokevirtual 122	java/lang/String:startsWith	(Ljava/lang/String;)Z
    //   99: ifeq +65 -> 164
    //   102: aload 4
    //   104: ldc 113
    //   106: invokeinterface 125 2 0
    //   111: istore_3
    //   112: iload_3
    //   113: iconst_m1
    //   114: if_icmpeq +63 -> 177
    //   117: aload 4
    //   119: iload_3
    //   120: invokeinterface 129 2 0
    //   125: astore 5
    //   127: aload 5
    //   129: invokestatic 135	android/text/TextUtils:isEmpty	(Ljava/lang/CharSequence;)Z
    //   132: ifne +45 -> 177
    //   135: new 101	java/io/File
    //   138: dup
    //   139: aload 5
    //   141: invokespecial 107	java/io/File:<init>	(Ljava/lang/String;)V
    //   144: astore 5
    //   146: aload 5
    //   148: astore_0
    //   149: aload 4
    //   151: ifnull -142 -> 9
    //   154: aload 4
    //   156: invokeinterface 65 1 0
    //   161: aload 5
    //   163: areturn
    //   164: aload 4
    //   166: ldc 111
    //   168: invokeinterface 125 2 0
    //   173: istore_3
    //   174: goto -62 -> 112
    //   177: aload 4
    //   179: ifnull +10 -> 189
    //   182: aload 4
    //   184: invokeinterface 65 1 0
    //   189: aconst_null
    //   190: areturn
    //   191: astore 5
    //   193: aload_0
    //   194: aload_1
    //   195: aload_2
    //   196: invokestatic 137	myobfuscated/cnz:b	(Landroid/content/Context;Landroid/content/ContentResolver;Landroid/net/Uri;)Ljava/io/File;
    //   199: astore_1
    //   200: aload_1
    //   201: astore_0
    //   202: aload 4
    //   204: ifnull -195 -> 9
    //   207: aload 4
    //   209: invokeinterface 65 1 0
    //   214: aload_1
    //   215: areturn
    //   216: astore_0
    //   217: aconst_null
    //   218: astore 4
    //   220: aload 4
    //   222: ifnull -33 -> 189
    //   225: aload 4
    //   227: invokeinterface 65 1 0
    //   232: goto -43 -> 189
    //   235: astore_0
    //   236: aconst_null
    //   237: astore 4
    //   239: aload 4
    //   241: ifnull +10 -> 251
    //   244: aload 4
    //   246: invokeinterface 65 1 0
    //   251: aload_0
    //   252: athrow
    //   253: astore_0
    //   254: goto -15 -> 239
    //   257: astore_0
    //   258: goto -19 -> 239
    //   261: astore_0
    //   262: goto -42 -> 220
    //   265: astore 5
    //   267: goto -74 -> 193
    // Local variable table:
    //   start	length	slot	name	signature
    //   0	270	0	paramContext	android.content.Context
    //   0	270	1	paramContentResolver	android.content.ContentResolver
    //   0	270	2	paramUri	android.net.Uri
    //   111	63	3	i	int
    //   1	244	4	localObject1	Object
    //   69	93	5	localObject2	Object
    //   191	1	5	localIllegalArgumentException1	IllegalArgumentException
    //   265	1	5	localIllegalArgumentException2	IllegalArgumentException
    // Exception table:
    //   from	to	target	type
    //   47	71	191	java/lang/IllegalArgumentException
    //   47	71	216	java/lang/SecurityException
    //   47	71	235	finally
    //   80	112	253	finally
    //   117	146	253	finally
    //   164	174	253	finally
    //   193	200	257	finally
    //   80	112	261	java/lang/SecurityException
    //   117	146	261	java/lang/SecurityException
    //   164	174	261	java/lang/SecurityException
    //   80	112	265	java/lang/IllegalArgumentException
    //   117	146	265	java/lang/IllegalArgumentException
    //   164	174	265	java/lang/IllegalArgumentException
  }
  
  public static void a(Closeable paramCloseable)
  {
    if (paramCloseable == null) {
      return;
    }
    try
    {
      paramCloseable.close();
      return;
    }
    catch (Throwable paramCloseable) {}
  }
  
  public static void a(cob paramcob, String paramString, Runnable paramRunnable, Handler paramHandler)
  {
    new Thread(new a(paramcob, paramRunnable, ProgressDialog.show(paramcob, null, paramString, true, false), paramHandler)).start();
  }
  
  /* Error */
  public static boolean a(java.io.File paramFile1, java.io.File paramFile2)
  {
    // Byte code:
    //   0: aload_0
    //   1: ifnull +7 -> 8
    //   4: aload_1
    //   5: ifnonnull +5 -> 10
    //   8: iconst_0
    //   9: ireturn
    //   10: new 71	myobfuscated/be
    //   13: dup
    //   14: aload_0
    //   15: invokevirtual 167	java/io/File:getAbsolutePath	()Ljava/lang/String;
    //   18: invokespecial 168	myobfuscated/be:<init>	(Ljava/lang/String;)V
    //   21: astore_0
    //   22: new 71	myobfuscated/be
    //   25: dup
    //   26: aload_1
    //   27: invokevirtual 167	java/io/File:getAbsolutePath	()Ljava/lang/String;
    //   30: invokespecial 168	myobfuscated/be:<init>	(Ljava/lang/String;)V
    //   33: astore 5
    //   35: aload_0
    //   36: ldc 76
    //   38: invokevirtual 171	myobfuscated/be:a	(Ljava/lang/String;)Ljava/lang/String;
    //   41: astore_0
    //   42: ldc -83
    //   44: ldc 76
    //   46: invokevirtual 99	java/lang/String:equals	(Ljava/lang/Object;)Z
    //   49: ifeq +1428 -> 1477
    //   52: ldc -81
    //   54: astore_1
    //   55: aload_0
    //   56: ifnull +1418 -> 1474
    //   59: getstatic 179	myobfuscated/be:i	Ljava/util/HashSet;
    //   62: aload_1
    //   63: invokevirtual 184	java/util/HashSet:contains	(Ljava/lang/Object;)Z
    //   66: ifeq +1408 -> 1474
    //   69: aload_1
    //   70: ldc -70
    //   72: invokevirtual 99	java/lang/String:equals	(Ljava/lang/Object;)Z
    //   75: ifeq +198 -> 273
    //   78: getstatic 190	myobfuscated/be:s	Ljava/util/regex/Pattern;
    //   81: aload_0
    //   82: invokevirtual 196	java/util/regex/Pattern:matcher	(Ljava/lang/CharSequence;)Ljava/util/regex/Matcher;
    //   85: astore 4
    //   87: aload 4
    //   89: invokevirtual 201	java/util/regex/Matcher:find	()Z
    //   92: ifne +53 -> 145
    //   95: new 203	java/lang/StringBuilder
    //   98: dup
    //   99: ldc -51
    //   101: invokespecial 206	java/lang/StringBuilder:<init>	(Ljava/lang/String;)V
    //   104: aload_1
    //   105: invokevirtual 210	java/lang/StringBuilder:append	(Ljava/lang/String;)Ljava/lang/StringBuilder;
    //   108: ldc -44
    //   110: invokevirtual 210	java/lang/StringBuilder:append	(Ljava/lang/String;)Ljava/lang/StringBuilder;
    //   113: aload_0
    //   114: invokevirtual 210	java/lang/StringBuilder:append	(Ljava/lang/String;)Ljava/lang/StringBuilder;
    //   117: pop
    //   118: aload 5
    //   120: getfield 216	myobfuscated/be:r	Z
    //   123: ifeq +12 -> 135
    //   126: aload 5
    //   128: getfield 220	myobfuscated/be:l	I
    //   131: iconst_4
    //   132: if_icmpeq +1111 -> 1243
    //   135: new 29	java/io/IOException
    //   138: dup
    //   139: ldc -34
    //   141: invokespecial 223	java/io/IOException:<init>	(Ljava/lang/String;)V
    //   144: athrow
    //   145: new 203	java/lang/StringBuilder
    //   148: dup
    //   149: invokespecial 224	java/lang/StringBuilder:<init>	()V
    //   152: aload 4
    //   154: iconst_1
    //   155: invokevirtual 227	java/util/regex/Matcher:group	(I)Ljava/lang/String;
    //   158: invokestatic 232	java/lang/Integer:parseInt	(Ljava/lang/String;)I
    //   161: invokevirtual 235	java/lang/StringBuilder:append	(I)Ljava/lang/StringBuilder;
    //   164: ldc -19
    //   166: invokevirtual 210	java/lang/StringBuilder:append	(Ljava/lang/String;)Ljava/lang/StringBuilder;
    //   169: aload 4
    //   171: iconst_2
    //   172: invokevirtual 227	java/util/regex/Matcher:group	(I)Ljava/lang/String;
    //   175: invokestatic 232	java/lang/Integer:parseInt	(Ljava/lang/String;)I
    //   178: invokevirtual 235	java/lang/StringBuilder:append	(I)Ljava/lang/StringBuilder;
    //   181: ldc -19
    //   183: invokevirtual 210	java/lang/StringBuilder:append	(Ljava/lang/String;)Ljava/lang/StringBuilder;
    //   186: aload 4
    //   188: iconst_3
    //   189: invokevirtual 227	java/util/regex/Matcher:group	(I)Ljava/lang/String;
    //   192: invokestatic 232	java/lang/Integer:parseInt	(Ljava/lang/String;)I
    //   195: invokevirtual 235	java/lang/StringBuilder:append	(I)Ljava/lang/StringBuilder;
    //   198: ldc -17
    //   200: invokevirtual 210	java/lang/StringBuilder:append	(Ljava/lang/String;)Ljava/lang/StringBuilder;
    //   203: invokevirtual 240	java/lang/StringBuilder:toString	()Ljava/lang/String;
    //   206: astore_0
    //   207: goto +1279 -> 1486
    //   210: iload_3
    //   211: getstatic 244	myobfuscated/be:g	[[Lmyobfuscated/be$d;
    //   214: arraylength
    //   215: if_icmpge -97 -> 118
    //   218: iload_3
    //   219: iconst_4
    //   220: if_icmpne +11 -> 231
    //   223: aload 5
    //   225: getfield 247	myobfuscated/be:o	Z
    //   228: ifeq +38 -> 266
    //   231: getstatic 251	myobfuscated/be:h	[Ljava/util/HashMap;
    //   234: iload_3
    //   235: aaload
    //   236: aload_1
    //   237: invokevirtual 257	java/util/HashMap:get	(Ljava/lang/Object;)Ljava/lang/Object;
    //   240: checkcast 259	myobfuscated/be$d
    //   243: astore 4
    //   245: aload 4
    //   247: ifnull +19 -> 266
    //   250: aload_0
    //   251: ifnonnull +73 -> 324
    //   254: aload 5
    //   256: getfield 262	myobfuscated/be:m	[Ljava/util/HashMap;
    //   259: iload_3
    //   260: aaload
    //   261: aload_1
    //   262: invokevirtual 265	java/util/HashMap:remove	(Ljava/lang/Object;)Ljava/lang/Object;
    //   265: pop
    //   266: iload_3
    //   267: iconst_1
    //   268: iadd
    //   269: istore_3
    //   270: goto -60 -> 210
    //   273: new 267	myobfuscated/be$e
    //   276: dup
    //   277: aload_0
    //   278: invokestatic 273	java/lang/Double:parseDouble	(Ljava/lang/String;)D
    //   281: iconst_0
    //   282: invokespecial 276	myobfuscated/be$e:<init>	(DB)V
    //   285: invokevirtual 277	myobfuscated/be$e:toString	()Ljava/lang/String;
    //   288: astore 4
    //   290: aload 4
    //   292: astore_0
    //   293: goto +1193 -> 1486
    //   296: astore 4
    //   298: new 203	java/lang/StringBuilder
    //   301: dup
    //   302: ldc -51
    //   304: invokespecial 206	java/lang/StringBuilder:<init>	(Ljava/lang/String;)V
    //   307: aload_1
    //   308: invokevirtual 210	java/lang/StringBuilder:append	(Ljava/lang/String;)Ljava/lang/StringBuilder;
    //   311: ldc -44
    //   313: invokevirtual 210	java/lang/StringBuilder:append	(Ljava/lang/String;)Ljava/lang/StringBuilder;
    //   316: aload_0
    //   317: invokevirtual 210	java/lang/StringBuilder:append	(Ljava/lang/String;)Ljava/lang/StringBuilder;
    //   320: pop
    //   321: goto -203 -> 118
    //   324: aload_0
    //   325: invokestatic 281	myobfuscated/be:c	(Ljava/lang/String;)Landroid/util/Pair;
    //   328: astore 6
    //   330: aload 4
    //   332: getfield 283	myobfuscated/be$d:c	I
    //   335: aload 6
    //   337: getfield 289	android/util/Pair:first	Ljava/lang/Object;
    //   340: checkcast 229	java/lang/Integer
    //   343: invokevirtual 292	java/lang/Integer:intValue	()I
    //   346: if_icmpeq +22 -> 368
    //   349: aload 4
    //   351: getfield 283	myobfuscated/be$d:c	I
    //   354: aload 6
    //   356: getfield 295	android/util/Pair:second	Ljava/lang/Object;
    //   359: checkcast 229	java/lang/Integer
    //   362: invokevirtual 292	java/lang/Integer:intValue	()I
    //   365: if_icmpne +87 -> 452
    //   368: aload 4
    //   370: getfield 283	myobfuscated/be$d:c	I
    //   373: istore_2
    //   374: goto +1117 -> 1491
    //   377: aload 5
    //   379: getfield 262	myobfuscated/be:m	[Ljava/util/HashMap;
    //   382: iload_3
    //   383: aaload
    //   384: astore 6
    //   386: aload_0
    //   387: invokevirtual 298	java/lang/String:length	()I
    //   390: iconst_1
    //   391: if_icmpne +338 -> 729
    //   394: aload_0
    //   395: iconst_0
    //   396: invokevirtual 302	java/lang/String:charAt	(I)C
    //   399: bipush 48
    //   401: if_icmplt +328 -> 729
    //   404: aload_0
    //   405: iconst_0
    //   406: invokevirtual 302	java/lang/String:charAt	(I)C
    //   409: bipush 49
    //   411: if_icmpgt +318 -> 729
    //   414: new 304	myobfuscated/be$c
    //   417: dup
    //   418: iconst_1
    //   419: iconst_1
    //   420: iconst_1
    //   421: newarray <illegal type>
    //   423: dup
    //   424: iconst_0
    //   425: aload_0
    //   426: iconst_0
    //   427: invokevirtual 302	java/lang/String:charAt	(I)C
    //   430: bipush 48
    //   432: isub
    //   433: i2b
    //   434: bastore
    //   435: invokespecial 307	myobfuscated/be$c:<init>	(II[B)V
    //   438: astore 4
    //   440: aload 6
    //   442: aload_1
    //   443: aload 4
    //   445: invokevirtual 311	java/util/HashMap:put	(Ljava/lang/Object;Ljava/lang/Object;)Ljava/lang/Object;
    //   448: pop
    //   449: goto -183 -> 266
    //   452: aload 4
    //   454: getfield 314	myobfuscated/be$d:d	I
    //   457: iconst_m1
    //   458: if_icmpeq +50 -> 508
    //   461: aload 4
    //   463: getfield 314	myobfuscated/be$d:d	I
    //   466: aload 6
    //   468: getfield 289	android/util/Pair:first	Ljava/lang/Object;
    //   471: checkcast 229	java/lang/Integer
    //   474: invokevirtual 292	java/lang/Integer:intValue	()I
    //   477: if_icmpeq +22 -> 499
    //   480: aload 4
    //   482: getfield 314	myobfuscated/be$d:d	I
    //   485: aload 6
    //   487: getfield 295	android/util/Pair:second	Ljava/lang/Object;
    //   490: checkcast 229	java/lang/Integer
    //   493: invokevirtual 292	java/lang/Integer:intValue	()I
    //   496: if_icmpne +12 -> 508
    //   499: aload 4
    //   501: getfield 314	myobfuscated/be$d:d	I
    //   504: istore_2
    //   505: goto +986 -> 1491
    //   508: aload 4
    //   510: getfield 283	myobfuscated/be$d:c	I
    //   513: iconst_1
    //   514: if_icmpeq +22 -> 536
    //   517: aload 4
    //   519: getfield 283	myobfuscated/be$d:c	I
    //   522: bipush 7
    //   524: if_icmpeq +12 -> 536
    //   527: aload 4
    //   529: getfield 283	myobfuscated/be$d:c	I
    //   532: iconst_2
    //   533: if_icmpne +12 -> 545
    //   536: aload 4
    //   538: getfield 283	myobfuscated/be$d:c	I
    //   541: istore_2
    //   542: goto +949 -> 1491
    //   545: new 203	java/lang/StringBuilder
    //   548: dup
    //   549: ldc_w 316
    //   552: invokespecial 206	java/lang/StringBuilder:<init>	(Ljava/lang/String;)V
    //   555: aload_1
    //   556: invokevirtual 210	java/lang/StringBuilder:append	(Ljava/lang/String;)Ljava/lang/StringBuilder;
    //   559: ldc_w 318
    //   562: invokevirtual 210	java/lang/StringBuilder:append	(Ljava/lang/String;)Ljava/lang/StringBuilder;
    //   565: getstatic 322	myobfuscated/be:e	[Ljava/lang/String;
    //   568: aload 4
    //   570: getfield 283	myobfuscated/be$d:c	I
    //   573: aaload
    //   574: invokevirtual 210	java/lang/StringBuilder:append	(Ljava/lang/String;)Ljava/lang/StringBuilder;
    //   577: astore 7
    //   579: aload 4
    //   581: getfield 314	myobfuscated/be$d:d	I
    //   584: iconst_m1
    //   585: if_icmpne +78 -> 663
    //   588: ldc_w 324
    //   591: astore 4
    //   593: aload 7
    //   595: aload 4
    //   597: invokevirtual 210	java/lang/StringBuilder:append	(Ljava/lang/String;)Ljava/lang/StringBuilder;
    //   600: ldc_w 326
    //   603: invokevirtual 210	java/lang/StringBuilder:append	(Ljava/lang/String;)Ljava/lang/StringBuilder;
    //   606: getstatic 322	myobfuscated/be:e	[Ljava/lang/String;
    //   609: aload 6
    //   611: getfield 289	android/util/Pair:first	Ljava/lang/Object;
    //   614: checkcast 229	java/lang/Integer
    //   617: invokevirtual 292	java/lang/Integer:intValue	()I
    //   620: aaload
    //   621: invokevirtual 210	java/lang/StringBuilder:append	(Ljava/lang/String;)Ljava/lang/StringBuilder;
    //   624: astore 7
    //   626: aload 6
    //   628: getfield 295	android/util/Pair:second	Ljava/lang/Object;
    //   631: checkcast 229	java/lang/Integer
    //   634: invokevirtual 292	java/lang/Integer:intValue	()I
    //   637: iconst_m1
    //   638: if_icmpne +55 -> 693
    //   641: ldc_w 324
    //   644: astore 4
    //   646: aload 7
    //   648: aload 4
    //   650: invokevirtual 210	java/lang/StringBuilder:append	(Ljava/lang/String;)Ljava/lang/StringBuilder;
    //   653: ldc_w 328
    //   656: invokevirtual 210	java/lang/StringBuilder:append	(Ljava/lang/String;)Ljava/lang/StringBuilder;
    //   659: pop
    //   660: goto -394 -> 266
    //   663: new 203	java/lang/StringBuilder
    //   666: dup
    //   667: ldc_w 330
    //   670: invokespecial 206	java/lang/StringBuilder:<init>	(Ljava/lang/String;)V
    //   673: getstatic 322	myobfuscated/be:e	[Ljava/lang/String;
    //   676: aload 4
    //   678: getfield 314	myobfuscated/be$d:d	I
    //   681: aaload
    //   682: invokevirtual 210	java/lang/StringBuilder:append	(Ljava/lang/String;)Ljava/lang/StringBuilder;
    //   685: invokevirtual 240	java/lang/StringBuilder:toString	()Ljava/lang/String;
    //   688: astore 4
    //   690: goto -97 -> 593
    //   693: new 203	java/lang/StringBuilder
    //   696: dup
    //   697: ldc_w 330
    //   700: invokespecial 206	java/lang/StringBuilder:<init>	(Ljava/lang/String;)V
    //   703: getstatic 322	myobfuscated/be:e	[Ljava/lang/String;
    //   706: aload 6
    //   708: getfield 295	android/util/Pair:second	Ljava/lang/Object;
    //   711: checkcast 229	java/lang/Integer
    //   714: invokevirtual 292	java/lang/Integer:intValue	()I
    //   717: aaload
    //   718: invokevirtual 210	java/lang/StringBuilder:append	(Ljava/lang/String;)Ljava/lang/StringBuilder;
    //   721: invokevirtual 240	java/lang/StringBuilder:toString	()Ljava/lang/String;
    //   724: astore 4
    //   726: goto -80 -> 646
    //   729: aload_0
    //   730: invokestatic 333	myobfuscated/be:b	()Ljava/nio/charset/Charset;
    //   733: invokevirtual 337	java/lang/String:getBytes	(Ljava/nio/charset/Charset;)[B
    //   736: astore 4
    //   738: new 304	myobfuscated/be$c
    //   741: dup
    //   742: iconst_1
    //   743: aload 4
    //   745: arraylength
    //   746: aload 4
    //   748: invokespecial 307	myobfuscated/be$c:<init>	(II[B)V
    //   751: astore 4
    //   753: goto -313 -> 440
    //   756: aload 5
    //   758: getfield 262	myobfuscated/be:m	[Ljava/util/HashMap;
    //   761: iload_3
    //   762: aaload
    //   763: aload_1
    //   764: aload_0
    //   765: invokestatic 340	myobfuscated/be$c:a	(Ljava/lang/String;)Lmyobfuscated/be$c;
    //   768: invokevirtual 311	java/util/HashMap:put	(Ljava/lang/Object;Ljava/lang/Object;)Ljava/lang/Object;
    //   771: pop
    //   772: goto -506 -> 266
    //   775: aload_0
    //   776: ldc_w 342
    //   779: invokevirtual 346	java/lang/String:split	(Ljava/lang/String;)[Ljava/lang/String;
    //   782: astore 4
    //   784: aload 4
    //   786: arraylength
    //   787: newarray <illegal type>
    //   789: astore 6
    //   791: iconst_0
    //   792: istore_2
    //   793: iload_2
    //   794: aload 4
    //   796: arraylength
    //   797: if_icmpge +21 -> 818
    //   800: aload 6
    //   802: iload_2
    //   803: aload 4
    //   805: iload_2
    //   806: aaload
    //   807: invokestatic 232	java/lang/Integer:parseInt	(Ljava/lang/String;)I
    //   810: iastore
    //   811: iload_2
    //   812: iconst_1
    //   813: iadd
    //   814: istore_2
    //   815: goto -22 -> 793
    //   818: aload 5
    //   820: getfield 262	myobfuscated/be:m	[Ljava/util/HashMap;
    //   823: iload_3
    //   824: aaload
    //   825: aload_1
    //   826: aload 6
    //   828: aload 5
    //   830: getfield 350	myobfuscated/be:n	Ljava/nio/ByteOrder;
    //   833: invokestatic 353	myobfuscated/be$c:a	([ILjava/nio/ByteOrder;)Lmyobfuscated/be$c;
    //   836: invokevirtual 311	java/util/HashMap:put	(Ljava/lang/Object;Ljava/lang/Object;)Ljava/lang/Object;
    //   839: pop
    //   840: goto -574 -> 266
    //   843: aload_0
    //   844: ldc_w 342
    //   847: invokevirtual 346	java/lang/String:split	(Ljava/lang/String;)[Ljava/lang/String;
    //   850: astore 4
    //   852: aload 4
    //   854: arraylength
    //   855: newarray <illegal type>
    //   857: astore 6
    //   859: iconst_0
    //   860: istore_2
    //   861: iload_2
    //   862: aload 4
    //   864: arraylength
    //   865: if_icmpge +21 -> 886
    //   868: aload 6
    //   870: iload_2
    //   871: aload 4
    //   873: iload_2
    //   874: aaload
    //   875: invokestatic 232	java/lang/Integer:parseInt	(Ljava/lang/String;)I
    //   878: iastore
    //   879: iload_2
    //   880: iconst_1
    //   881: iadd
    //   882: istore_2
    //   883: goto -22 -> 861
    //   886: aload 5
    //   888: getfield 262	myobfuscated/be:m	[Ljava/util/HashMap;
    //   891: iload_3
    //   892: aaload
    //   893: aload_1
    //   894: aload 6
    //   896: aload 5
    //   898: getfield 350	myobfuscated/be:n	Ljava/nio/ByteOrder;
    //   901: invokestatic 355	myobfuscated/be$c:b	([ILjava/nio/ByteOrder;)Lmyobfuscated/be$c;
    //   904: invokevirtual 311	java/util/HashMap:put	(Ljava/lang/Object;Ljava/lang/Object;)Ljava/lang/Object;
    //   907: pop
    //   908: goto -642 -> 266
    //   911: aload_0
    //   912: ldc_w 342
    //   915: invokevirtual 346	java/lang/String:split	(Ljava/lang/String;)[Ljava/lang/String;
    //   918: astore 4
    //   920: aload 4
    //   922: arraylength
    //   923: newarray <illegal type>
    //   925: astore 6
    //   927: iconst_0
    //   928: istore_2
    //   929: iload_2
    //   930: aload 4
    //   932: arraylength
    //   933: if_icmpge +21 -> 954
    //   936: aload 6
    //   938: iload_2
    //   939: aload 4
    //   941: iload_2
    //   942: aaload
    //   943: invokestatic 361	java/lang/Long:parseLong	(Ljava/lang/String;)J
    //   946: lastore
    //   947: iload_2
    //   948: iconst_1
    //   949: iadd
    //   950: istore_2
    //   951: goto -22 -> 929
    //   954: aload 5
    //   956: getfield 262	myobfuscated/be:m	[Ljava/util/HashMap;
    //   959: iload_3
    //   960: aaload
    //   961: aload_1
    //   962: aload 6
    //   964: aload 5
    //   966: getfield 350	myobfuscated/be:n	Ljava/nio/ByteOrder;
    //   969: invokestatic 364	myobfuscated/be$c:a	([JLjava/nio/ByteOrder;)Lmyobfuscated/be$c;
    //   972: invokevirtual 311	java/util/HashMap:put	(Ljava/lang/Object;Ljava/lang/Object;)Ljava/lang/Object;
    //   975: pop
    //   976: goto -710 -> 266
    //   979: aload_0
    //   980: ldc_w 342
    //   983: invokevirtual 346	java/lang/String:split	(Ljava/lang/String;)[Ljava/lang/String;
    //   986: astore 4
    //   988: aload 4
    //   990: arraylength
    //   991: anewarray 267	myobfuscated/be$e
    //   994: astore 6
    //   996: iconst_0
    //   997: istore_2
    //   998: iload_2
    //   999: aload 4
    //   1001: arraylength
    //   1002: if_icmpge +50 -> 1052
    //   1005: aload 4
    //   1007: iload_2
    //   1008: aaload
    //   1009: ldc_w 366
    //   1012: invokevirtual 346	java/lang/String:split	(Ljava/lang/String;)[Ljava/lang/String;
    //   1015: astore 7
    //   1017: aload 6
    //   1019: iload_2
    //   1020: new 267	myobfuscated/be$e
    //   1023: dup
    //   1024: aload 7
    //   1026: iconst_0
    //   1027: aaload
    //   1028: invokestatic 273	java/lang/Double:parseDouble	(Ljava/lang/String;)D
    //   1031: d2l
    //   1032: aload 7
    //   1034: iconst_1
    //   1035: aaload
    //   1036: invokestatic 273	java/lang/Double:parseDouble	(Ljava/lang/String;)D
    //   1039: d2l
    //   1040: iconst_0
    //   1041: invokespecial 369	myobfuscated/be$e:<init>	(JJB)V
    //   1044: aastore
    //   1045: iload_2
    //   1046: iconst_1
    //   1047: iadd
    //   1048: istore_2
    //   1049: goto -51 -> 998
    //   1052: aload 5
    //   1054: getfield 262	myobfuscated/be:m	[Ljava/util/HashMap;
    //   1057: iload_3
    //   1058: aaload
    //   1059: aload_1
    //   1060: aload 6
    //   1062: aload 5
    //   1064: getfield 350	myobfuscated/be:n	Ljava/nio/ByteOrder;
    //   1067: invokestatic 372	myobfuscated/be$c:a	([Lmyobfuscated/be$e;Ljava/nio/ByteOrder;)Lmyobfuscated/be$c;
    //   1070: invokevirtual 311	java/util/HashMap:put	(Ljava/lang/Object;Ljava/lang/Object;)Ljava/lang/Object;
    //   1073: pop
    //   1074: goto -808 -> 266
    //   1077: aload_0
    //   1078: ldc_w 342
    //   1081: invokevirtual 346	java/lang/String:split	(Ljava/lang/String;)[Ljava/lang/String;
    //   1084: astore 4
    //   1086: aload 4
    //   1088: arraylength
    //   1089: anewarray 267	myobfuscated/be$e
    //   1092: astore 6
    //   1094: iconst_0
    //   1095: istore_2
    //   1096: iload_2
    //   1097: aload 4
    //   1099: arraylength
    //   1100: if_icmpge +50 -> 1150
    //   1103: aload 4
    //   1105: iload_2
    //   1106: aaload
    //   1107: ldc_w 366
    //   1110: invokevirtual 346	java/lang/String:split	(Ljava/lang/String;)[Ljava/lang/String;
    //   1113: astore 7
    //   1115: aload 6
    //   1117: iload_2
    //   1118: new 267	myobfuscated/be$e
    //   1121: dup
    //   1122: aload 7
    //   1124: iconst_0
    //   1125: aaload
    //   1126: invokestatic 273	java/lang/Double:parseDouble	(Ljava/lang/String;)D
    //   1129: d2l
    //   1130: aload 7
    //   1132: iconst_1
    //   1133: aaload
    //   1134: invokestatic 273	java/lang/Double:parseDouble	(Ljava/lang/String;)D
    //   1137: d2l
    //   1138: iconst_0
    //   1139: invokespecial 369	myobfuscated/be$e:<init>	(JJB)V
    //   1142: aastore
    //   1143: iload_2
    //   1144: iconst_1
    //   1145: iadd
    //   1146: istore_2
    //   1147: goto -51 -> 1096
    //   1150: aload 5
    //   1152: getfield 262	myobfuscated/be:m	[Ljava/util/HashMap;
    //   1155: iload_3
    //   1156: aaload
    //   1157: aload_1
    //   1158: aload 6
    //   1160: aload 5
    //   1162: getfield 350	myobfuscated/be:n	Ljava/nio/ByteOrder;
    //   1165: invokestatic 374	myobfuscated/be$c:b	([Lmyobfuscated/be$e;Ljava/nio/ByteOrder;)Lmyobfuscated/be$c;
    //   1168: invokevirtual 311	java/util/HashMap:put	(Ljava/lang/Object;Ljava/lang/Object;)Ljava/lang/Object;
    //   1171: pop
    //   1172: goto -906 -> 266
    //   1175: aload_0
    //   1176: ldc_w 342
    //   1179: invokevirtual 346	java/lang/String:split	(Ljava/lang/String;)[Ljava/lang/String;
    //   1182: astore 4
    //   1184: aload 4
    //   1186: arraylength
    //   1187: newarray <illegal type>
    //   1189: astore 6
    //   1191: iconst_0
    //   1192: istore_2
    //   1193: iload_2
    //   1194: aload 4
    //   1196: arraylength
    //   1197: if_icmpge +21 -> 1218
    //   1200: aload 6
    //   1202: iload_2
    //   1203: aload 4
    //   1205: iload_2
    //   1206: aaload
    //   1207: invokestatic 273	java/lang/Double:parseDouble	(Ljava/lang/String;)D
    //   1210: dastore
    //   1211: iload_2
    //   1212: iconst_1
    //   1213: iadd
    //   1214: istore_2
    //   1215: goto -22 -> 1193
    //   1218: aload 5
    //   1220: getfield 262	myobfuscated/be:m	[Ljava/util/HashMap;
    //   1223: iload_3
    //   1224: aaload
    //   1225: aload_1
    //   1226: aload 6
    //   1228: aload 5
    //   1230: getfield 350	myobfuscated/be:n	Ljava/nio/ByteOrder;
    //   1233: invokestatic 377	myobfuscated/be$c:a	([DLjava/nio/ByteOrder;)Lmyobfuscated/be$c;
    //   1236: invokevirtual 311	java/util/HashMap:put	(Ljava/lang/Object;Ljava/lang/Object;)Ljava/lang/Object;
    //   1239: pop
    //   1240: goto -974 -> 266
    //   1243: aload 5
    //   1245: getfield 380	myobfuscated/be:k	Ljava/lang/String;
    //   1248: ifnonnull +14 -> 1262
    //   1251: new 29	java/io/IOException
    //   1254: dup
    //   1255: ldc_w 382
    //   1258: invokespecial 223	java/io/IOException:<init>	(Ljava/lang/String;)V
    //   1261: athrow
    //   1262: aload 5
    //   1264: getfield 385	myobfuscated/be:q	I
    //   1267: bipush 6
    //   1269: if_icmpeq +13 -> 1282
    //   1272: aload 5
    //   1274: getfield 385	myobfuscated/be:q	I
    //   1277: bipush 7
    //   1279: if_icmpne +97 -> 1376
    //   1282: aload 5
    //   1284: invokevirtual 388	myobfuscated/be:a	()[B
    //   1287: astore_0
    //   1288: aload 5
    //   1290: aload_0
    //   1291: putfield 392	myobfuscated/be:p	[B
    //   1294: new 101	java/io/File
    //   1297: dup
    //   1298: new 203	java/lang/StringBuilder
    //   1301: dup
    //   1302: invokespecial 224	java/lang/StringBuilder:<init>	()V
    //   1305: aload 5
    //   1307: getfield 380	myobfuscated/be:k	Ljava/lang/String;
    //   1310: invokevirtual 210	java/lang/StringBuilder:append	(Ljava/lang/String;)Ljava/lang/StringBuilder;
    //   1313: ldc_w 394
    //   1316: invokevirtual 210	java/lang/StringBuilder:append	(Ljava/lang/String;)Ljava/lang/StringBuilder;
    //   1319: invokevirtual 240	java/lang/StringBuilder:toString	()Ljava/lang/String;
    //   1322: invokespecial 107	java/io/File:<init>	(Ljava/lang/String;)V
    //   1325: astore 6
    //   1327: new 101	java/io/File
    //   1330: dup
    //   1331: aload 5
    //   1333: getfield 380	myobfuscated/be:k	Ljava/lang/String;
    //   1336: invokespecial 107	java/io/File:<init>	(Ljava/lang/String;)V
    //   1339: aload 6
    //   1341: invokevirtual 398	java/io/File:renameTo	(Ljava/io/File;)Z
    //   1344: ifne +37 -> 1381
    //   1347: new 29	java/io/IOException
    //   1350: dup
    //   1351: new 203	java/lang/StringBuilder
    //   1354: dup
    //   1355: ldc_w 400
    //   1358: invokespecial 206	java/lang/StringBuilder:<init>	(Ljava/lang/String;)V
    //   1361: aload 6
    //   1363: invokevirtual 167	java/io/File:getAbsolutePath	()Ljava/lang/String;
    //   1366: invokevirtual 210	java/lang/StringBuilder:append	(Ljava/lang/String;)Ljava/lang/StringBuilder;
    //   1369: invokevirtual 240	java/lang/StringBuilder:toString	()Ljava/lang/String;
    //   1372: invokespecial 223	java/io/IOException:<init>	(Ljava/lang/String;)V
    //   1375: athrow
    //   1376: aconst_null
    //   1377: astore_0
    //   1378: goto -90 -> 1288
    //   1381: new 402	java/io/FileInputStream
    //   1384: dup
    //   1385: aload 6
    //   1387: invokespecial 405	java/io/FileInputStream:<init>	(Ljava/io/File;)V
    //   1390: astore_0
    //   1391: new 407	java/io/FileOutputStream
    //   1394: dup
    //   1395: aload 5
    //   1397: getfield 380	myobfuscated/be:k	Ljava/lang/String;
    //   1400: invokespecial 408	java/io/FileOutputStream:<init>	(Ljava/lang/String;)V
    //   1403: astore_1
    //   1404: aload 5
    //   1406: aload_0
    //   1407: aload_1
    //   1408: invokevirtual 411	myobfuscated/be:a	(Ljava/io/InputStream;Ljava/io/OutputStream;)V
    //   1411: aload_0
    //   1412: invokestatic 413	myobfuscated/be:a	(Ljava/io/Closeable;)V
    //   1415: aload_1
    //   1416: invokestatic 413	myobfuscated/be:a	(Ljava/io/Closeable;)V
    //   1419: aload 6
    //   1421: invokevirtual 416	java/io/File:delete	()Z
    //   1424: pop
    //   1425: aload 5
    //   1427: aconst_null
    //   1428: putfield 392	myobfuscated/be:p	[B
    //   1431: iconst_1
    //   1432: ireturn
    //   1433: aload 4
    //   1435: invokestatic 413	myobfuscated/be:a	(Ljava/io/Closeable;)V
    //   1438: aload_1
    //   1439: invokestatic 413	myobfuscated/be:a	(Ljava/io/Closeable;)V
    //   1442: aload 6
    //   1444: invokevirtual 416	java/io/File:delete	()Z
    //   1447: pop
    //   1448: aload_0
    //   1449: athrow
    //   1450: astore 5
    //   1452: aconst_null
    //   1453: astore_1
    //   1454: aload_0
    //   1455: astore 4
    //   1457: aload 5
    //   1459: astore_0
    //   1460: goto -27 -> 1433
    //   1463: astore 5
    //   1465: aload_0
    //   1466: astore 4
    //   1468: aload 5
    //   1470: astore_0
    //   1471: goto -38 -> 1433
    //   1474: goto +12 -> 1486
    //   1477: ldc 76
    //   1479: astore_1
    //   1480: goto -1425 -> 55
    //   1483: astore_0
    //   1484: iconst_0
    //   1485: ireturn
    //   1486: iconst_0
    //   1487: istore_3
    //   1488: goto -1278 -> 210
    //   1491: iload_2
    //   1492: tableswitch	default:+64->1556, 1:+-1115->377, 2:+-736->756, 3:+-717->775, 4:+-581->911, 5:+-513->979, 6:+64->1556, 7:+-736->756, 8:+64->1556, 9:+-649->843, 10:+-415->1077, 11:+64->1556, 12:+-317->1175
    //   1556: goto -1290 -> 266
    //   1559: astore_0
    //   1560: aconst_null
    //   1561: astore 4
    //   1563: aconst_null
    //   1564: astore_1
    //   1565: goto -132 -> 1433
    // Local variable table:
    //   start	length	slot	name	signature
    //   0	1568	0	paramFile1	java.io.File
    //   0	1568	1	paramFile2	java.io.File
    //   373	1119	2	i	int
    //   210	1278	3	j	int
    //   85	206	4	localObject1	Object
    //   296	73	4	localNumberFormatException	NumberFormatException
    //   438	1124	4	localObject2	Object
    //   33	1393	5	localbe	be
    //   1450	8	5	localObject3	Object
    //   1463	6	5	localObject4	Object
    //   328	1115	6	localObject5	Object
    //   577	554	7	localObject6	Object
    // Exception table:
    //   from	to	target	type
    //   273	290	296	java/lang/NumberFormatException
    //   1391	1404	1450	finally
    //   1404	1411	1463	finally
    //   10	52	1483	java/io/IOException
    //   59	118	1483	java/io/IOException
    //   118	135	1483	java/io/IOException
    //   135	145	1483	java/io/IOException
    //   145	207	1483	java/io/IOException
    //   210	218	1483	java/io/IOException
    //   223	231	1483	java/io/IOException
    //   231	245	1483	java/io/IOException
    //   254	266	1483	java/io/IOException
    //   273	290	1483	java/io/IOException
    //   298	321	1483	java/io/IOException
    //   324	368	1483	java/io/IOException
    //   368	374	1483	java/io/IOException
    //   377	440	1483	java/io/IOException
    //   440	449	1483	java/io/IOException
    //   452	499	1483	java/io/IOException
    //   499	505	1483	java/io/IOException
    //   508	536	1483	java/io/IOException
    //   536	542	1483	java/io/IOException
    //   545	588	1483	java/io/IOException
    //   593	641	1483	java/io/IOException
    //   646	660	1483	java/io/IOException
    //   663	690	1483	java/io/IOException
    //   693	726	1483	java/io/IOException
    //   729	753	1483	java/io/IOException
    //   756	772	1483	java/io/IOException
    //   775	791	1483	java/io/IOException
    //   793	811	1483	java/io/IOException
    //   818	840	1483	java/io/IOException
    //   843	859	1483	java/io/IOException
    //   861	879	1483	java/io/IOException
    //   886	908	1483	java/io/IOException
    //   911	927	1483	java/io/IOException
    //   929	947	1483	java/io/IOException
    //   954	976	1483	java/io/IOException
    //   979	996	1483	java/io/IOException
    //   998	1045	1483	java/io/IOException
    //   1052	1074	1483	java/io/IOException
    //   1077	1094	1483	java/io/IOException
    //   1096	1143	1483	java/io/IOException
    //   1150	1172	1483	java/io/IOException
    //   1175	1191	1483	java/io/IOException
    //   1193	1211	1483	java/io/IOException
    //   1218	1240	1483	java/io/IOException
    //   1243	1262	1483	java/io/IOException
    //   1262	1282	1483	java/io/IOException
    //   1282	1288	1483	java/io/IOException
    //   1288	1376	1483	java/io/IOException
    //   1411	1431	1483	java/io/IOException
    //   1433	1450	1483	java/io/IOException
    //   1381	1391	1559	finally
  }
  
  /* Error */
  private static java.io.File b(android.content.Context paramContext, android.content.ContentResolver paramContentResolver, android.net.Uri paramUri)
  {
    // Byte code:
    //   0: aload_2
    //   1: ifnonnull +5 -> 6
    //   4: aconst_null
    //   5: areturn
    //   6: new 402	java/io/FileInputStream
    //   9: dup
    //   10: aload_1
    //   11: aload_2
    //   12: ldc_w 417
    //   15: invokevirtual 421	android/content/ContentResolver:openFileDescriptor	(Landroid/net/Uri;Ljava/lang/String;)Landroid/os/ParcelFileDescriptor;
    //   18: invokevirtual 427	android/os/ParcelFileDescriptor:getFileDescriptor	()Ljava/io/FileDescriptor;
    //   21: invokespecial 430	java/io/FileInputStream:<init>	(Ljava/io/FileDescriptor;)V
    //   24: astore_1
    //   25: ldc_w 432
    //   28: ldc_w 434
    //   31: aload_0
    //   32: invokevirtual 438	android/content/Context:getCacheDir	()Ljava/io/File;
    //   35: invokestatic 442	java/io/File:createTempFile	(Ljava/lang/String;Ljava/lang/String;Ljava/io/File;)Ljava/io/File;
    //   38: invokevirtual 167	java/io/File:getAbsolutePath	()Ljava/lang/String;
    //   41: astore_0
    //   42: new 407	java/io/FileOutputStream
    //   45: dup
    //   46: aload_0
    //   47: invokespecial 408	java/io/FileOutputStream:<init>	(Ljava/lang/String;)V
    //   50: astore_2
    //   51: sipush 4096
    //   54: newarray <illegal type>
    //   56: astore 4
    //   58: aload_1
    //   59: aload 4
    //   61: invokevirtual 446	java/io/FileInputStream:read	([B)I
    //   64: istore_3
    //   65: iload_3
    //   66: iconst_m1
    //   67: if_icmpeq +27 -> 94
    //   70: aload_2
    //   71: aload 4
    //   73: iconst_0
    //   74: iload_3
    //   75: invokevirtual 450	java/io/FileOutputStream:write	([BII)V
    //   78: goto -20 -> 58
    //   81: astore_0
    //   82: aload_2
    //   83: astore_0
    //   84: aload_1
    //   85: invokestatic 451	myobfuscated/cnz:a	(Ljava/io/Closeable;)V
    //   88: aload_0
    //   89: invokestatic 451	myobfuscated/cnz:a	(Ljava/io/Closeable;)V
    //   92: aconst_null
    //   93: areturn
    //   94: new 101	java/io/File
    //   97: dup
    //   98: aload_0
    //   99: invokespecial 107	java/io/File:<init>	(Ljava/lang/String;)V
    //   102: astore_0
    //   103: aload_1
    //   104: invokestatic 451	myobfuscated/cnz:a	(Ljava/io/Closeable;)V
    //   107: aload_2
    //   108: invokestatic 451	myobfuscated/cnz:a	(Ljava/io/Closeable;)V
    //   111: aload_0
    //   112: areturn
    //   113: astore_0
    //   114: aconst_null
    //   115: astore_2
    //   116: aconst_null
    //   117: astore_1
    //   118: aload_1
    //   119: invokestatic 451	myobfuscated/cnz:a	(Ljava/io/Closeable;)V
    //   122: aload_2
    //   123: invokestatic 451	myobfuscated/cnz:a	(Ljava/io/Closeable;)V
    //   126: aload_0
    //   127: athrow
    //   128: astore_0
    //   129: aconst_null
    //   130: astore_2
    //   131: goto -13 -> 118
    //   134: astore_0
    //   135: goto -17 -> 118
    //   138: astore_0
    //   139: aconst_null
    //   140: astore_0
    //   141: aconst_null
    //   142: astore_1
    //   143: goto -59 -> 84
    //   146: astore_0
    //   147: aconst_null
    //   148: astore_0
    //   149: goto -65 -> 84
    // Local variable table:
    //   start	length	slot	name	signature
    //   0	152	0	paramContext	android.content.Context
    //   0	152	1	paramContentResolver	android.content.ContentResolver
    //   0	152	2	paramUri	android.net.Uri
    //   64	11	3	i	int
    //   56	16	4	arrayOfByte	byte[]
    // Exception table:
    //   from	to	target	type
    //   51	58	81	java/io/IOException
    //   58	65	81	java/io/IOException
    //   70	78	81	java/io/IOException
    //   94	103	81	java/io/IOException
    //   6	25	113	finally
    //   25	51	128	finally
    //   51	58	134	finally
    //   58	65	134	finally
    //   70	78	134	finally
    //   94	103	134	finally
    //   6	25	138	java/io/IOException
    //   25	51	146	java/io/IOException
  }
  
  static final class a
    extends cob.a
    implements Runnable
  {
    final cob a;
    final ProgressDialog b;
    private final Runnable c;
    private final Handler d;
    private final Runnable e = new Runnable()
    {
      public final void run()
      {
        cnz.a.this.a.a(cnz.a.this);
        if (cnz.a.this.b.getWindow() != null) {
          cnz.a.this.b.dismiss();
        }
      }
    };
    
    public a(cob paramcob, Runnable paramRunnable, ProgressDialog paramProgressDialog, Handler paramHandler)
    {
      this.a = paramcob;
      this.b = paramProgressDialog;
      this.c = paramRunnable;
      this.a.b(this);
      this.d = paramHandler;
    }
    
    public final void a()
    {
      this.e.run();
      this.d.removeCallbacks(this.e);
    }
    
    public final void b()
    {
      this.b.hide();
    }
    
    public final void c()
    {
      this.b.show();
    }
    
    public final void run()
    {
      try
      {
        this.c.run();
        return;
      }
      finally
      {
        this.d.post(this.e);
      }
    }
  }
}


/* Location:              C:\dex2jar-2.0\classes-dex2jar.jar!\myobfuscated\cnz.class
 * Java compiler version: 6 (50.0)
 * JD-Core Version:       0.7.1
 */